<annotation>
	<folder>roData</folder>
	<filename>CDIC_RETRO_1 (208).jpg</filename>
	<path>D:\roData\CDIC_RETRO_1 (208).jpg</path>
	<source>
		<database>Unknown</database>
	</source>
	<size>
		<width>1960</width>
		<height>4032</height>
		<depth>3</depth>
	</size>
	<segmented>0</segmented>
	<object>
		<name>CDIC_retro</name>
		<pose>Unspecified</pose>
		<truncated>0</truncated>
		<difficult>0</difficult>
		<robndbox>
			<cx>786.9955</cx>
			<cy>1868.4034</cy>
			<w>1818.5536</w>
			<h>1295.1999</h>
			<angle>1.474936</angle>
		</robndbox>
		<extra/>
	</object>
</annotation>
